qdatastream.py
qdatastream-0.1.2.dist-info/DESCRIPTION.rst
qdatastream-0.1.2.dist-info/METADATA
qdatastream-0.1.2.dist-info/RECORD
qdatastream-0.1.2.dist-info/WHEEL
qdatastream-0.1.2.dist-info/metadata.json
qdatastream-0.1.2.dist-info/top_level.txt
qdatastream-0.1.2.dist-info/zip-safe
