Metadata-Version: 2.0
Name: qdatastream
Version: 0.1.2
Summary: pure python implementation for Qt's QDataStream
Home-page: http://github/hgoldfish/qdatastream
Author: Qize Huang
Author-email: hgoldfish@gmail.com
License: LGPL
Keywords: qt qdatastream
Platform: UNKNOWN
Classifier: Development Status :: 4 - Beta
Classifier: Environment :: Console
Classifier: Intended Audience :: Developers
Classifier: Operating System :: MacOS :: MacOS X
Classifier: Operating System :: Microsoft :: Windows
Classifier: Operating System :: POSIX
Classifier: Programming Language :: Python
